aegis_framework/__init__.py
aegis_framework/core/__init__.py
aegis_framework/core/design_agent.py
aegis_framework/core/master_agent.py
aegis_framework/core/ollama_model.py
aegis_framework/core/__pycache__/__init__.cpython-312.pyc
aegis_framework/core/__pycache__/design_agent.cpython-312.pyc
aegis_framework/core/__pycache__/master_agent.cpython-312.pyc
aegis_framework/core/__pycache__/ollama_model.cpython-312.pyc
aegis_framework/public/__init__.py
aegis_framework/public/design_agent.py
aegis_framework/public/master_agent.py
aegis_framework/public/ollama_model.py
aegis_framework/public/__pycache__/__init__.cpython-312.pyc
aegis_framework/public/__pycache__/design_agent.cpython-312.pyc
aegis_framework/public/__pycache__/master_agent.cpython-312.pyc
aegis_framework/public/__pycache__/ollama_model.cpython-312.pyc
aegis_framework-0.1.18.dist-info/LICENSE
aegis_framework-0.1.18.dist-info/METADATA
aegis_framework-0.1.18.dist-info/WHEEL
aegis_framework-0.1.18.dist-info/top_level.txt
aegis_framework-0.1.18.dist-info/RECORD
