Metadata-Version: 2.1
Name: aegis-framework
Version: 0.1.18
Summary: A comprehensive, extensible AI agent framework with local LLM integration
Home-page: https://github.com/metisos/aegis-framework
Author: Metis Analytics
Author-email: cjohnson@metisos.com
Project-URL: Bug Tracker, https://github.com/metisos/aegis-framework/issues
Keywords: ai,agents,llm,machine-learning,artificial-intelligence,multi-agent,ollama
Classifier: Development Status :: 4 - Beta
Classifier: Intended Audience :: Developers
Classifier: Intended Audience :: Science/Research
Classifier: License :: OSI Approved :: MIT License
Classifier: Operating System :: OS Independent
Classifier: Programming Language :: Python :: 3
Classifier: Programming Language :: Python :: 3.7
Classifier: Programming Language :: Python :: 3.8
Classifier: Programming Language :: Python :: 3.9
Classifier: Programming Language :: Python :: 3.10
Classifier: Programming Language :: Python :: 3.12
Classifier: Topic :: Software Development :: Libraries :: Python Modules
Classifier: Topic :: Scientific/Engineering :: Artificial Intelligence
Requires-Python: >=3.7
License-File: LICENSE
Requires-Dist: typing>=3.7.4
Requires-Dist: requests>=2.25.0
Requires-Dist: fuzzywuzzy>=0.18.0
Requires-Dist: python-Levenshtein>=0.12.0
Requires-Dist: sqlite3-api>=2.0.1
Requires-Dist: numpy>=1.19.0
Requires-Dist: pandas>=1.3.0
Provides-Extra: web
Requires-Dist: flask>=2.0.0; extra == "web"
Requires-Dist: flask-socketio>=5.0.0; extra == "web"
Requires-Dist: eventlet>=0.30.0; extra == "web"
Provides-Extra: data
Requires-Dist: numpy>=1.19.0; extra == "data"
Requires-Dist: pandas>=1.3.0; extra == "data"
Requires-Dist: matplotlib>=3.3.0; extra == "data"
Requires-Dist: seaborn>=0.11.0; extra == "data"
Provides-Extra: llm
Requires-Dist: ollama>=0.1.0; extra == "llm"
Requires-Dist: transformers>=4.0.0; extra == "llm"
Provides-Extra: dev
Requires-Dist: pytest>=6.0.0; extra == "dev"
Requires-Dist: black>=21.0.0; extra == "dev"
Requires-Dist: isort>=5.0.0; extra == "dev"
Requires-Dist: mypy>=0.900; extra == "dev"
Requires-Dist: flake8>=3.9.0; extra == "dev"
